dash/__init__.py
dash/_callback.py
dash/_callback_context.py
dash/_configs.py
dash/_dash_renderer.py
dash/_get_app.py
dash/_get_paths.py
dash/_grouping.py
dash/_hooks.py
dash/_jupyter.py
dash/_obsolete.py
dash/_pages.py
dash/_patch.py
dash/_utils.py
dash/_validate.py
dash/_watch.py
dash/dash.py
dash/dependencies.py
dash/exceptions.py
dash/extract-meta.js
dash/favicon.ico
dash/fingerprint.py
dash/py.typed
dash/resources.py
dash/types.py
dash/version.py
dash/background_callback/__init__.py
dash/background_callback/_proxy_set_props.py
dash/background_callback/managers/__init__.py
dash/background_callback/managers/celery_manager.py
dash/background_callback/managers/diskcache_manager.py
dash/dash-renderer/build/dash_renderer.dev.js
dash/dash-renderer/build/dash_renderer.min.js
dash/dash_table/.gitkeep
dash/dash_table/DataTable.py
dash/dash_table/Format.py
dash/dash_table/FormatTemplate.py
dash/dash_table/__init__.py
dash/dash_table/_imports_.py
dash/dash_table/async-export.js
dash/dash_table/async-export.js.LICENSE.txt
dash/dash_table/async-export.js.map
dash/dash_table/async-highlight.js
dash/dash_table/async-highlight.js.map
dash/dash_table/async-table.js
dash/dash_table/async-table.js.LICENSE.txt
dash/dash_table/async-table.js.map
dash/dash_table/bundle.js
dash/dash_table/bundle.js.map
dash/dash_table/demo.js
dash/dash_table/demo.js.map
dash/dash_table/index.html
dash/dash_table/metadata.json
dash/dash_table/package-info.json
dash/dcc/.gitkeep
dash/dcc/Checklist.py
dash/dcc/Clipboard.py
dash/dcc/ConfirmDialog.py
dash/dcc/ConfirmDialogProvider.py
dash/dcc/DatePickerRange.py
dash/dcc/DatePickerSingle.py
dash/dcc/Download.py
dash/dcc/Dropdown.py
dash/dcc/Geolocation.py
dash/dcc/Graph.py
dash/dcc/Input.py
dash/dcc/Interval.py
dash/dcc/Link.py
dash/dcc/Loading.py
dash/dcc/Location.py
dash/dcc/Markdown.py
dash/dcc/RadioItems.py
dash/dcc/RangeSlider.py
dash/dcc/Slider.py
dash/dcc/Store.py
dash/dcc/Tab.py
dash/dcc/Tabs.py
dash/dcc/Textarea.py
dash/dcc/Tooltip.py
dash-3.1.1.dist-info/LICENSE
dash-3.1.1.dist-info/METADATA
dash-3.1.1.dist-info/WHEEL
dash-3.1.1.dist-info/entry_points.txt
dash-3.1.1.dist-info/top_level.txt
dash-3.1.1.dist-info/RECORD
