Metadata-Version: 2.1
Name: dash
Version: 3.1.1
Summary: A Python framework for building reactive web-apps. Developed by Plotly.
Home-page: https://plotly.com/dash
Author: Chris Parmer
Author-email: chris@plotly.com
License: MIT
Project-URL: Documentation, https://dash.plotly.com
Project-URL: Source, https://github.com/plotly/dash
Project-URL: Issue Tracker, https://github.com/plotly/dash/issues
Platform: UNKNOWN
Classifier: Development Status :: 5 - Production/Stable
Classifier: Environment :: Web Environment
Classifier: Framework :: Dash
Classifier: Framework :: Flask
Classifier: Intended Audience :: Developers
Classifier: Intended Audience :: Education
Classifier: Intended Audience :: Financial and Insurance Industry
Classifier: Intended Audience :: Healthcare Industry
Classifier: Intended Audience :: Manufacturing
Classifier: Intended Audience :: Science/Research
Classifier: License :: OSI Approved :: MIT License
Classifier: Programming Language :: Python
Classifier: Programming Language :: Python :: 3
Classifier: Programming Language :: Python :: 3.8
Classifier: Programming Language :: Python :: 3.9
Classifier: Programming Language :: Python :: 3.10
Classifier: Programming Language :: Python :: 3.11
Classifier: Programming Language :: Python :: 3.12
Classifier: Topic :: Database :: Front-Ends
Classifier: Topic :: Office/Business :: Financial :: Spreadsheet
Classifier: Topic :: Scientific/Engineering :: Visualization
Classifier: Topic :: Software Development :: Libraries :: Application Frameworks
Classifier: Topic :: Software Development :: Widget Sets
Requires-Python: >=3.8
Provides-Extra: async
Provides-Extra: ci
Provides-Extra: dev
Provides-Extra: testing
Provides-Extra: celery
Provides-Extra: diskcache
Provides-Extra: compress
License-File: LICENSE
